thenvoi_rest/__init__.py
thenvoi_rest/agent_api/__init__.py
thenvoi_rest/agent_api/client.py
thenvoi_rest/agent_api/raw_client.py
thenvoi_rest/agent_api/types/__init__.py
thenvoi_rest/agent_api/types/add_agent_chat_participant_response.py
thenvoi_rest/agent_api/types/create_agent_chat_event_response.py
thenvoi_rest/agent_api/types/create_agent_chat_message_response.py
thenvoi_rest/agent_api/types/create_agent_chat_response.py
thenvoi_rest/agent_api/types/get_agent_chat_context_response.py
thenvoi_rest/agent_api/types/get_agent_chat_context_response_meta.py
thenvoi_rest/agent_api/types/get_agent_chat_response.py
thenvoi_rest/agent_api/types/get_agent_me_response.py
thenvoi_rest/agent_api/types/get_agent_next_message_response.py
thenvoi_rest/agent_api/types/list_agent_chat_participants_response.py
thenvoi_rest/agent_api/types/list_agent_chats_response.py
thenvoi_rest/agent_api/types/list_agent_chats_response_metadata.py
thenvoi_rest/agent_api/types/list_agent_messages_request_status.py
thenvoi_rest/agent_api/types/list_agent_messages_response.py
thenvoi_rest/agent_api/types/list_agent_messages_response_metadata.py
thenvoi_rest/agent_api/types/list_agent_peers_response.py
thenvoi_rest/agent_api/types/list_agent_peers_response_metadata.py
thenvoi_rest/agent_api/types/mark_agent_message_failed_response.py
thenvoi_rest/agent_api/types/mark_agent_message_processed_response.py
thenvoi_rest/agent_api/types/mark_agent_message_processing_response.py
thenvoi_rest/agent_api/types/remove_agent_chat_participant_response.py
thenvoi_rest/client.py
thenvoi_rest/core/__init__.py
thenvoi_rest/core/api_error.py
thenvoi_rest/core/client_wrapper.py
thenvoi_rest/core/datetime_utils.py
thenvoi_rest/core/file.py
thenvoi_rest/core/force_multipart.py
thenvoi_rest/core/http_client.py
thenvoi_rest/core/http_response.py
thenvoi_rest/core/http_sse/__init__.py
thenvoi_rest/core/http_sse/_api.py
thenvoi_rest/core/http_sse/_decoders.py
thenvoi_rest/core/http_sse/_exceptions.py
thenvoi_client_rest-0.0.2.dist-info/METADATA
thenvoi_client_rest-0.0.2.dist-info/WHEEL
thenvoi_client_rest-0.0.2.dist-info/RECORD
